reqwizard/__init__.py
reqwizard/cli.py
reqwizard-0.1.2.dist-info/licenses/LICENSE
reqwizard-0.1.2.dist-info/METADATA
reqwizard-0.1.2.dist-info/WHEEL
reqwizard-0.1.2.dist-info/entry_points.txt
reqwizard-0.1.2.dist-info/top_level.txt
reqwizard-0.1.2.dist-info/RECORD
