Metadata-Version: 2.4
Name: reqwizard
Version: 0.1.2
Summary: Automatic dependency installer for Python projects. Instalador automático de dependências para projetos Python.
Author-email: MrEddwolf <viana.edu@live.com>
License: MIT License (English)
Project-URL: Homepage, https://github.com/MrEddwolf/reqwizard
Project-URL: Repository, https://github.com/MrEddwolf/reqwizard
Project-URL: Changelog, https://github.com/MrEddwolf/reqwizard/blob/main/README.md#changelog
Project-URL: License, https://github.com/MrEddwolf/reqwizard/blob/main/LICENSE
Keywords: dependency,installer,python,reqs,yaml
Classifier: Programming Language :: Python :: 3
Classifier: License :: OSI Approved :: MIT License
Classifier: Operating System :: OS Independent
Requires-Python: >=3.10
License-File: LICENSE
Requires-Dist: packaging
Requires-Dist: requests
Requires-Dist: tomli
Dynamic: license-file
